micro_vad_cpp.abi3.so
pymicro_vad/__init__.py
pymicro_vad/py.typed
pymicro_vad-2.0.1.dist-info/METADATA
pymicro_vad-2.0.1.dist-info/WHEEL
pymicro_vad-2.0.1.dist-info/top_level.txt
pymicro_vad-2.0.1.dist-info/RECORD
pymicro_vad-2.0.1.dist-info/licenses/LICENSE
