Metadata-Version: 2.4
Name: pymicro-vad
Version: 2.0.1
Summary: Self-contained voice activity detector
Home-page: https://github.com/rhasspy/pymicro-vad
Author: Michael Hansen
Author-email: mike@rhasspy.org
License: Apache
Requires-Python: >=3.9
License-File: LICENSE
Provides-Extra: dev
Requires-Dist: black; extra == "dev"
Requires-Dist: flake8; extra == "dev"
Requires-Dist: isort; extra == "dev"
Requires-Dist: mypy; extra == "dev"
Requires-Dist: pylint; extra == "dev"
Requires-Dist: pytest; extra == "dev"
Requires-Dist: build; extra == "dev"
Dynamic: license-file
Dynamic: provides-extra
